{
  "name": "betterdeserttemples:snowy/snowy/main",
  "fallback": "minecraft:empty",
  "elements": [
    {
      "weight": 1,
      "element": {
        "location": "betterdeserttemples:snowy/main/top_center",
        "processors": "betterdeserttemples:snowy/main",
        "projection": "rigid",
        "element_type": "minecraft:single_pool_element"
      }
    },
    {
      "weight": 1,
      "element": {
        "location": "betterdeserttemples:snowy/main/front_puzzle_connector",
        "processors": "betterdeserttemples:snowy/main",
        "projection": "rigid",
        "element_type": "minecraft:single_pool_element"
      }
    },
    {
      "weight": 1,
      "element": {
        "location": "betterdeserttemples:snowy/main/left_puzzle_connector",
        "processors": "betterdeserttemples:snowy/main",
        "projection": "rigid",
        "element_type": "minecraft:single_pool_element"
      }
    },
    {
      "weight": 1,
      "element": {
        "location": "betterdeserttemples:snowy/main/right_puzzle_connector",
        "processors": "betterdeserttemples:snowy/main",
        "projection": "rigid",
        "element_type": "minecraft:single_pool_element"
      }
    },
    {
      "weight": 1,
      "element": {
        "location": "betterdeserttemples:snowy/main/main_corner",
        "processors": "betterdeserttemples:snowy/main",
        "projection": "rigid",
        "element_type": "minecraft:single_pool_element"
      }
    },
    {
      "weight": 1,
      "element": {
        "location": "betterdeserttemples:snowy/main/main_entrance_corner_left",
        "processors": "betterdeserttemples:snowy/main",
        "projection": "rigid",
        "element_type": "minecraft:single_pool_element"
      }
    },
    {
      "weight": 1,
      "element": {
        "location": "betterdeserttemples:snowy/main/main_entrance_corner_right",
        "processors": "betterdeserttemples:snowy/main",
        "projection": "rigid",
        "element_type": "minecraft:single_pool_element"
      }
    },
    {
      "weight": 1,
      "element": {
        "location": "betterdeserttemples:snowy/main/main_corner_top",
        "processors": "betterdeserttemples:snowy/main",
        "projection": "rigid",
        "element_type": "minecraft:single_pool_element"
      }
    },
    {
      "weight": 1,
      "element": {
        "location": "betterdeserttemples:snowy/main/main_puzzle_connector_top",
        "processors": "betterdeserttemples:snowy/main",
        "projection": "rigid",
        "element_type": "minecraft:single_pool_element"
      }
    },
    {
      "weight": 1,
      "element": {
        "location": "betterdeserttemples:snowy/main/main_puzzle_top",
        "processors": "betterdeserttemples:snowy/main",
        "projection": "rigid",
        "element_type": "minecraft:single_pool_element"
      }
    },
    {
      "weight": 1,
      "element": {
        "location": "betterdeserttemples:snowy/main/entrance_connector",
        "processors": "betterdeserttemples:snowy/main",
        "projection": "rigid",
        "element_type": "minecraft:single_pool_element"
      }
    },
    {
      "weight": 1,
      "element": {
        "location": "betterdeserttemples:snowy/main/balcony_straight",
        "processors": "betterdeserttemples:snowy/main",
        "projection": "rigid",
        "element_type": "minecraft:single_pool_element"
      }
    },
    {
      "weight": 1,
      "element": {
        "location": "betterdeserttemples:snowy/main/main_entrance_cover",
        "processors": "betterdeserttemples:snowy/main",
        "projection": "rigid",
        "element_type": "minecraft:single_pool_element"
      }
    },
    {
      "weight": 1,
      "element": {
        "location": "betterdeserttemples:snowy/main/outside_left",
        "processors": "betterdeserttemples:snowy/main",
        "projection": "rigid",
        "element_type": "minecraft:single_pool_element"
      }
    },
    {
      "weight": 1,
      "element": {
        "location": "betterdeserttemples:snowy/main/outside_right",
        "processors": "betterdeserttemples:snowy/main",
        "projection": "rigid",
        "element_type": "minecraft:single_pool_element"
      }
    },
    {
      "weight": 1,
      "element": {
        "location": "betterdeserttemples:snowy/main/bottom_entrance_corner/bottom_left_entrance_corner_0",
        "processors": "betterdeserttemples:snowy/main",
        "projection": "rigid",
        "element_type": "minecraft:single_pool_element"
      }
    },
    {
      "weight": 1,
      "element": {
        "location": "betterdeserttemples:snowy/main/bottom_entrance_corner/bottom_left_entrance_corner_1",
        "processors": "betterdeserttemples:snowy/main",
        "projection": "rigid",
        "element_type": "minecraft:single_pool_element"
      }
    },
    {
      "weight": 1,
      "element": {
        "location": "betterdeserttemples:snowy/main/bottom_entrance_corner/bottom_left_entrance_corner_2",
        "processors": "betterdeserttemples:snowy/main",
        "projection": "rigid",
        "element_type": "minecraft:single_pool_element"
      }
    },
    {
      "weight": 1,
      "element": {
        "location": "betterdeserttemples:snowy/main/bottom_entrance_corner/bottom_left_entrance_corner_3",
        "processors": "betterdeserttemples:snowy/main",
        "projection": "rigid",
        "element_type": "minecraft:single_pool_element"
      }
    },
    {
      "weight": 1,
      "element": {
        "location": "betterdeserttemples:snowy/main/bottom_left_entrance_corner_front",
        "processors": "betterdeserttemples:snowy/main",
        "projection": "rigid",
        "element_type": "minecraft:single_pool_element"
      }
    },
    {
      "weight": 1,
      "element": {
        "location": "betterdeserttemples:snowy/main/bottom_entrance_corner/bottom_right_entrance_corner_0",
        "processors": "betterdeserttemples:snowy/main",
        "projection": "rigid",
        "element_type": "minecraft:single_pool_element"
      }
    },
    {
      "weight": 1,
      "element": {
        "location": "betterdeserttemples:snowy/main/bottom_entrance_corner/bottom_right_entrance_corner_1",
        "processors": "betterdeserttemples:snowy/main",
        "projection": "rigid",
        "element_type": "minecraft:single_pool_element"
      }
    },
    {
      "weight": 1,
      "element": {
        "location": "betterdeserttemples:snowy/main/bottom_right_entrance_corner_front",
        "processors": "betterdeserttemples:snowy/main",
        "projection": "rigid",
        "element_type": "minecraft:single_pool_element"
      }
    },
    {
      "weight": 1,
      "element": {
        "location": "betterdeserttemples:snowy/main/bottom_main_corner/bottom_right_main_corner_0",
        "processors": "betterdeserttemples:snowy/main",
        "projection": "rigid",
        "element_type": "minecraft:single_pool_element"
      }
    },
    {
      "weight": 1,
      "element": {
        "location": "betterdeserttemples:snowy/main/bottom_main_corner/bottom_right_main_corner_1",
        "processors": "betterdeserttemples:snowy/main",
        "projection": "rigid",
        "element_type": "minecraft:single_pool_element"
      }
    },
    {
      "weight": 1,
      "element": {
        "location": "betterdeserttemples:snowy/main/bottom_main_corner/bottom_right_main_corner_2",
        "processors": "betterdeserttemples:snowy/main",
        "projection": "rigid",
        "element_type": "minecraft:single_pool_element"
      }
    },
    {
      "weight": 1,
      "element": {
        "location": "betterdeserttemples:snowy/main/bottom_main_corner/bottom_right_main_corner_3",
        "processors": "betterdeserttemples:snowy/main",
        "projection": "rigid",
        "element_type": "minecraft:single_pool_element"
      }
    },
    {
      "weight": 1,
      "element": {
        "location": "betterdeserttemples:snowy/main/bottom_main_corner/bottom_left_main_corner_0",
        "processors": "betterdeserttemples:snowy/main",
        "projection": "rigid",
        "element_type": "minecraft:single_pool_element"
      }
    },
    {
      "weight": 1,
      "element": {
        "location": "betterdeserttemples:snowy/main/bottom_main_corner/bottom_left_main_corner_1",
        "processors": "betterdeserttemples:snowy/main",
        "projection": "rigid",
        "element_type": "minecraft:single_pool_element"
      }
    },
    {
      "weight": 1,
      "element": {
        "location": "betterdeserttemples:snowy/main/bottom_main_corner_front",
        "processors": "betterdeserttemples:snowy/main",
        "projection": "rigid",
        "element_type": "minecraft:single_pool_element"
      }
    },
    {
      "weight": 1,
      "element": {
        "location": "betterdeserttemples:snowy/main/bottom_entrance_corner_side",
        "processors": "betterdeserttemples:snowy/main",
        "projection": "rigid",
        "element_type": "minecraft:single_pool_element"
      }
    },
    {
      "weight": 1,
      "element": {
        "location": "betterdeserttemples:snowy/main/hall_entrance_corridor",
        "processors": "betterdeserttemples:snowy/main",
        "projection": "rigid",
        "element_type": "minecraft:single_pool_element"
      }
    },
    {
      "weight": 1,
      "element": {
        "location": "betterdeserttemples:snowy/main/statue_corner",
        "processors": "betterdeserttemples:snowy/main",
        "projection": "rigid",
        "element_type": "minecraft:single_pool_element"
      }
    },
    {
      "weight": 1,
      "element": {
        "location": "betterdeserttemples:snowy/main/statue_corner_empty",
        "processors": "betterdeserttemples:snowy/main",
        "projection": "rigid",
        "element_type": "minecraft:single_pool_element"
      }
    },
    {
      "weight": 1,
      "element": {
        "location": "betterdeserttemples:snowy/main/tnt_bottom",
        "processors": "betterdeserttemples:snowy/main",
        "projection": "rigid",
        "element_type": "minecraft:single_pool_element"
      }
    }
  ]
}