{
    "bookshelf:load_conditions": [
      {
        "type": "bookshelf:item_exists",
        "values": [
          "byg:holly_sapling"
        ]
      }
    ],
    "type": "botanypots:crop",
    "seed": {
      "item": "byg:holly_sapling"
    },
    "categories": [
      "dirt"
    ],
    "growthTicks": 2400,
    "display": {
      "block": "byg:holly_sapling"
    },
    "drops": [
      {
        "chance": 1.00,
        "output": {
          "item": "byg:holly_log"
        },
        "minRolls": 2,
        "maxRolls": 4
    },
    {
      "chance": 0.20,
      "output": {
        "item": "minecraft:stick"
      },
      "minRolls": 1,
      "maxRolls": 2
    },
    {
      "chance": 0.20,
      "output": {
        "item": "byg:holly_berries"
      },
      "minRolls": 1,
      "maxRolls": 2
    },
    {
        "chance": 0.01,
        "output": {
          "item": "byg:holly_sapling"
        }
      }
    ]
  }
